setup.py
pylongecity/__init__.py
pylongecity/helpers.py
pylongecity/scraper.py
pylongecity/styles.py
pylongecity.egg-info/PKG-INFO
pylongecity.egg-info/SOURCES.txt
pylongecity.egg-info/dependency_links.txt
pylongecity.egg-info/top_level.txt