Metadata-Version: 1.1
Name: pylongecity
Version: 0.1.1
Summary: A simple script to quickly search longecity threads for relevant information
Home-page: http://github.com/cyrbon/pylongecity
Author: Jon Chase
Author-email: code.cyrbon@gmail.com
License: Apache 2.0
Download-URL: https://github.com/cyrbon/pylongecity/tarball/0.1.1
Platform: UNKNOWN
